twos_complement_practice/__init__.py
twos_complement_practice/twos_complement.py
twos_complement_practice-1.0.3.dist-info/licenses/LICENSE
twos_complement_practice-1.0.3.dist-info/METADATA
twos_complement_practice-1.0.3.dist-info/WHEEL
twos_complement_practice-1.0.3.dist-info/entry_points.txt
twos_complement_practice-1.0.3.dist-info/top_level.txt
twos_complement_practice-1.0.3.dist-info/RECORD
