Metadata-Version: 2.4
Name: twos_complement_practice
Version: 1.0.3
Summary: CLI tool for practicing two's complement representation of signed integers
Author-email: Clayton Cafiero <cbcafier@uvm.edu>
License: GPL-3.0-or-later
Project-URL: Homepage, https://gitlab.com/ccafiero/twos_complement_practice
Classifier: Programming Language :: Python :: 3
Classifier: Intended Audience :: Education
Classifier: License :: OSI Approved :: GNU General Public License v3 (GPLv3)
Classifier: Operating System :: OS Independent
Requires-Python: >=3.9
License-File: LICENSE
Requires-Dist: colorama>=0.4
Provides-Extra: dev
Requires-Dist: coverage; extra == "dev"
Requires-Dist: pytest; extra == "dev"
Requires-Dist: flake8; extra == "dev"
Requires-Dist: pylint; extra == "dev"
Requires-Dist: build; extra == "dev"
Dynamic: license-file
